<annotation>
	<folder>data</folder>
	<filename>frameDual Universe 2020-09-10 18-42-24.mp4425.png</filename>
	<path>F:\Python\PycharmProjects\OreDetection\data\frameDual Universe 2020-09-10 18-42-24.mp4425.png</path>
	<source>
		<database>Unknown</database>
	</source>
	<size>
		<width>1728</width>
		<height>1080</height>
		<depth>3</depth>
	</size>
	<segmented>0</segmented>
	<object>
		<name>Ore</name>
		<pose>Unspecified</pose>
		<truncated>0</truncated>
		<difficult>0</difficult>
		<bndbox>
			<xmin>770</xmin>
			<ymin>513</ymin>
			<xmax>980</xmax>
			<ymax>721</ymax>
		</bndbox>
	</object>
	<object>
		<name>Ore</name>
		<pose>Unspecified</pose>
		<truncated>0</truncated>
		<difficult>0</difficult>
		<bndbox>
			<xmin>1205</xmin>
			<ymin>500</ymin>
			<xmax>1403</xmax>
			<ymax>594</ymax>
		</bndbox>
	</object>
	<object>
		<name>Ore</name>
		<pose>Unspecified</pose>
		<truncated>0</truncated>
		<difficult>0</difficult>
		<bndbox>
			<xmin>955</xmin>
			<ymin>719</ymin>
			<xmax>1326</xmax>
			<ymax>1055</ymax>
		</bndbox>
	</object>
	<object>
		<name>Ore</name>
		<pose>Unspecified</pose>
		<truncated>0</truncated>
		<difficult>0</difficult>
		<bndbox>
			<xmin>393</xmin>
			<ymin>297</ymin>
			<xmax>510</xmax>
			<ymax>366</ymax>
		</bndbox>
	</object>
	<object>
		<name>Ore</name>
		<pose>Unspecified</pose>
		<truncated>0</truncated>
		<difficult>0</difficult>
		<bndbox>
			<xmin>647</xmin>
			<ymin>179</ymin>
			<xmax>705</xmax>
			<ymax>213</ymax>
		</bndbox>
	</object>
	<object>
		<name>Ore</name>
		<pose>Unspecified</pose>
		<truncated>0</truncated>
		<difficult>0</difficult>
		<bndbox>
			<xmin>501</xmin>
			<ymin>187</ymin>
			<xmax>539</xmax>
			<ymax>209</ymax>
		</bndbox>
	</object>
	<object>
		<name>Ore</name>
		<pose>Unspecified</pose>
		<truncated>0</truncated>
		<difficult>0</difficult>
		<bndbox>
			<xmin>350</xmin>
			<ymin>176</ymin>
			<xmax>422</xmax>
			<ymax>208</ymax>
		</bndbox>
	</object>
	<object>
		<name>Ore</name>
		<pose>Unspecified</pose>
		<truncated>0</truncated>
		<difficult>0</difficult>
		<bndbox>
			<xmin>9</xmin>
			<ymin>342</ymin>
			<xmax>176</xmax>
			<ymax>466</ymax>
		</bndbox>
	</object>
	<object>
		<name>Ore</name>
		<pose>Unspecified</pose>
		<truncated>0</truncated>
		<difficult>0</difficult>
		<bndbox>
			<xmin>5</xmin>
			<ymin>291</ymin>
			<xmax>40</xmax>
			<ymax>346</ymax>
		</bndbox>
	</object>
	<object>
		<name>Ore</name>
		<pose>Unspecified</pose>
		<truncated>0</truncated>
		<difficult>0</difficult>
		<bndbox>
			<xmin>5</xmin>
			<ymin>526</ymin>
			<xmax>109</xmax>
			<ymax>647</ymax>
		</bndbox>
	</object>
	<object>
		<name>Ore</name>
		<pose>Unspecified</pose>
		<truncated>1</truncated>
		<difficult>0</difficult>
		<bndbox>
			<xmin>1</xmin>
			<ymin>862</ymin>
			<xmax>246</xmax>
			<ymax>1074</ymax>
		</bndbox>
	</object>
</annotation>
