<annotation>
	<folder>data</folder>
	<filename>frameDual Universe 2020-09-10 18-42-24.mp4399.png</filename>
	<path>F:\Python\PycharmProjects\OreDetection\data\frameDual Universe 2020-09-10 18-42-24.mp4399.png</path>
	<source>
		<database>Unknown</database>
	</source>
	<size>
		<width>1728</width>
		<height>1080</height>
		<depth>3</depth>
	</size>
	<segmented>0</segmented>
	<object>
		<name>Ore</name>
		<pose>Unspecified</pose>
		<truncated>0</truncated>
		<difficult>0</difficult>
		<bndbox>
			<xmin>1263</xmin>
			<ymin>622</ymin>
			<xmax>1712</xmax>
			<ymax>972</ymax>
		</bndbox>
	</object>
	<object>
		<name>Ore</name>
		<pose>Unspecified</pose>
		<truncated>0</truncated>
		<difficult>0</difficult>
		<bndbox>
			<xmin>1101</xmin>
			<ymin>422</ymin>
			<xmax>1338</xmax>
			<ymax>600</ymax>
		</bndbox>
	</object>
	<object>
		<name>Ore</name>
		<pose>Unspecified</pose>
		<truncated>1</truncated>
		<difficult>0</difficult>
		<bndbox>
			<xmin>1616</xmin>
			<ymin>423</ymin>
			<xmax>1728</xmax>
			<ymax>537</ymax>
		</bndbox>
	</object>
	<object>
		<name>Ore</name>
		<pose>Unspecified</pose>
		<truncated>0</truncated>
		<difficult>0</difficult>
		<bndbox>
			<xmin>205</xmin>
			<ymin>620</ymin>
			<xmax>622</xmax>
			<ymax>970</ymax>
		</bndbox>
	</object>
	<object>
		<name>Ore</name>
		<pose>Unspecified</pose>
		<truncated>0</truncated>
		<difficult>0</difficult>
		<bndbox>
			<xmin>109</xmin>
			<ymin>460</ymin>
			<xmax>327</xmax>
			<ymax>633</ymax>
		</bndbox>
	</object>
	<object>
		<name>Ore</name>
		<pose>Unspecified</pose>
		<truncated>0</truncated>
		<difficult>0</difficult>
		<bndbox>
			<xmin>369</xmin>
			<ymin>385</ymin>
			<xmax>544</xmax>
			<ymax>508</ymax>
		</bndbox>
	</object>
	<object>
		<name>Ore</name>
		<pose>Unspecified</pose>
		<truncated>0</truncated>
		<difficult>0</difficult>
		<bndbox>
			<xmin>311</xmin>
			<ymin>302</ymin>
			<xmax>429</xmax>
			<ymax>438</ymax>
		</bndbox>
	</object>
	<object>
		<name>Ore</name>
		<pose>Unspecified</pose>
		<truncated>0</truncated>
		<difficult>0</difficult>
		<bndbox>
			<xmin>465</xmin>
			<ymin>234</ymin>
			<xmax>583</xmax>
			<ymax>347</ymax>
		</bndbox>
	</object>
	<object>
		<name>Ore</name>
		<pose>Unspecified</pose>
		<truncated>0</truncated>
		<difficult>0</difficult>
		<bndbox>
			<xmin>766</xmin>
			<ymin>186</ymin>
			<xmax>871</xmax>
			<ymax>251</ymax>
		</bndbox>
	</object>
	<object>
		<name>Ore</name>
		<pose>Unspecified</pose>
		<truncated>0</truncated>
		<difficult>0</difficult>
		<bndbox>
			<xmin>428</xmin>
			<ymin>187</ymin>
			<xmax>491</xmax>
			<ymax>241</ymax>
		</bndbox>
	</object>
	<object>
		<name>Ore</name>
		<pose>Unspecified</pose>
		<truncated>0</truncated>
		<difficult>0</difficult>
		<bndbox>
			<xmin>409</xmin>
			<ymin>171</ymin>
			<xmax>450</xmax>
			<ymax>207</ymax>
		</bndbox>
	</object>
	<object>
		<name>Ore</name>
		<pose>Unspecified</pose>
		<truncated>0</truncated>
		<difficult>0</difficult>
		<bndbox>
			<xmin>297</xmin>
			<ymin>219</ymin>
			<xmax>345</xmax>
			<ymax>250</ymax>
		</bndbox>
	</object>
	<object>
		<name>Ore</name>
		<pose>Unspecified</pose>
		<truncated>0</truncated>
		<difficult>0</difficult>
		<bndbox>
			<xmin>155</xmin>
			<ymin>291</ymin>
			<xmax>227</xmax>
			<ymax>332</ymax>
		</bndbox>
	</object>
	<object>
		<name>Ore</name>
		<pose>Unspecified</pose>
		<truncated>0</truncated>
		<difficult>0</difficult>
		<bndbox>
			<xmin>143</xmin>
			<ymin>343</ymin>
			<xmax>189</xmax>
			<ymax>380</ymax>
		</bndbox>
	</object>
	<object>
		<name>Ore</name>
		<pose>Unspecified</pose>
		<truncated>0</truncated>
		<difficult>0</difficult>
		<bndbox>
			<xmin>2</xmin>
			<ymin>400</ymin>
			<xmax>71</xmax>
			<ymax>438</ymax>
		</bndbox>
	</object>
	<object>
		<name>Ore</name>
		<pose>Unspecified</pose>
		<truncated>1</truncated>
		<difficult>0</difficult>
		<bndbox>
			<xmin>1</xmin>
			<ymin>270</ymin>
			<xmax>57</xmax>
			<ymax>302</ymax>
		</bndbox>
	</object>
	<object>
		<name>Ore</name>
		<pose>Unspecified</pose>
		<truncated>0</truncated>
		<difficult>0</difficult>
		<bndbox>
			<xmin>290</xmin>
			<ymin>140</ymin>
			<xmax>350</xmax>
			<ymax>188</ymax>
		</bndbox>
	</object>
	<object>
		<name>Ore</name>
		<pose>Unspecified</pose>
		<truncated>0</truncated>
		<difficult>0</difficult>
		<bndbox>
			<xmin>732</xmin>
			<ymin>77</ymin>
			<xmax>789</xmax>
			<ymax>106</ymax>
		</bndbox>
	</object>
</annotation>
