<annotation>
	<folder>data</folder>
	<filename>frameDual Universe 2020-09-10 18-42-24.mp41276.png</filename>
	<path>F:\Python\PycharmProjects\OreDetection\data\frameDual Universe 2020-09-10 18-42-24.mp41276.png</path>
	<source>
		<database>Unknown</database>
	</source>
	<size>
		<width>1728</width>
		<height>1080</height>
		<depth>3</depth>
	</size>
	<segmented>0</segmented>
	<object>
		<name>Ore</name>
		<pose>Unspecified</pose>
		<truncated>0</truncated>
		<difficult>0</difficult>
		<bndbox>
			<xmin>763</xmin>
			<ymin>473</ymin>
			<xmax>959</xmax>
			<ymax>702</ymax>
		</bndbox>
	</object>
	<object>
		<name>Ore</name>
		<pose>Unspecified</pose>
		<truncated>0</truncated>
		<difficult>0</difficult>
		<bndbox>
			<xmin>1191</xmin>
			<ymin>441</ymin>
			<xmax>1463</xmax>
			<ymax>653</ymax>
		</bndbox>
	</object>
	<object>
		<name>Ore</name>
		<pose>Unspecified</pose>
		<truncated>0</truncated>
		<difficult>0</difficult>
		<bndbox>
			<xmin>994</xmin>
			<ymin>308</ymin>
			<xmax>1147</xmax>
			<ymax>538</ymax>
		</bndbox>
	</object>
	<object>
		<name>Ore</name>
		<pose>Unspecified</pose>
		<truncated>0</truncated>
		<difficult>0</difficult>
		<bndbox>
			<xmin>663</xmin>
			<ymin>308</ymin>
			<xmax>722</xmax>
			<ymax>417</ymax>
		</bndbox>
	</object>
	<object>
		<name>Ore</name>
		<pose>Unspecified</pose>
		<truncated>0</truncated>
		<difficult>0</difficult>
		<bndbox>
			<xmin>729</xmin>
			<ymin>277</ymin>
			<xmax>893</xmax>
			<ymax>372</ymax>
		</bndbox>
	</object>
</annotation>
