<annotation>
	<folder>data</folder>
	<filename>frameDual Universe 2020-09-10 18-42-24.mp4553.png</filename>
	<path>F:\Python\PycharmProjects\OreDetection\data\frameDual Universe 2020-09-10 18-42-24.mp4553.png</path>
	<source>
		<database>Unknown</database>
	</source>
	<size>
		<width>1728</width>
		<height>1080</height>
		<depth>3</depth>
	</size>
	<segmented>0</segmented>
	<object>
		<name>Ore</name>
		<pose>Unspecified</pose>
		<truncated>0</truncated>
		<difficult>0</difficult>
		<bndbox>
			<xmin>1042</xmin>
			<ymin>547</ymin>
			<xmax>1205</xmax>
			<ymax>647</ymax>
		</bndbox>
	</object>
	<object>
		<name>Ore</name>
		<pose>Unspecified</pose>
		<truncated>0</truncated>
		<difficult>0</difficult>
		<bndbox>
			<xmin>777</xmin>
			<ymin>243</ymin>
			<xmax>922</xmax>
			<ymax>340</ymax>
		</bndbox>
	</object>
	<object>
		<name>Ore</name>
		<pose>Unspecified</pose>
		<truncated>0</truncated>
		<difficult>0</difficult>
		<bndbox>
			<xmin>335</xmin>
			<ymin>312</ymin>
			<xmax>499</xmax>
			<ymax>469</ymax>
		</bndbox>
	</object>
	<object>
		<name>Ore</name>
		<pose>Unspecified</pose>
		<truncated>0</truncated>
		<difficult>0</difficult>
		<bndbox>
			<xmin>381</xmin>
			<ymin>242</ymin>
			<xmax>452</xmax>
			<ymax>309</ymax>
		</bndbox>
	</object>
	<object>
		<name>Ore</name>
		<pose>Unspecified</pose>
		<truncated>0</truncated>
		<difficult>0</difficult>
		<bndbox>
			<xmin>375</xmin>
			<ymin>225</ymin>
			<xmax>426</xmax>
			<ymax>268</ymax>
		</bndbox>
	</object>
	<object>
		<name>Ore</name>
		<pose>Unspecified</pose>
		<truncated>0</truncated>
		<difficult>0</difficult>
		<bndbox>
			<xmin>265</xmin>
			<ymin>316</ymin>
			<xmax>317</xmax>
			<ymax>350</ymax>
		</bndbox>
	</object>
	<object>
		<name>Ore</name>
		<pose>Unspecified</pose>
		<truncated>0</truncated>
		<difficult>0</difficult>
		<bndbox>
			<xmin>241</xmin>
			<ymin>282</ymin>
			<xmax>288</xmax>
			<ymax>315</ymax>
		</bndbox>
	</object>
	<object>
		<name>Ore</name>
		<pose>Unspecified</pose>
		<truncated>0</truncated>
		<difficult>0</difficult>
		<bndbox>
			<xmin>29</xmin>
			<ymin>375</ymin>
			<xmax>109</xmax>
			<ymax>418</ymax>
		</bndbox>
	</object>
	<object>
		<name>Ore</name>
		<pose>Unspecified</pose>
		<truncated>1</truncated>
		<difficult>0</difficult>
		<bndbox>
			<xmin>1</xmin>
			<ymin>431</ymin>
			<xmax>251</xmax>
			<ymax>664</ymax>
		</bndbox>
	</object>
	<object>
		<name>Ore</name>
		<pose>Unspecified</pose>
		<truncated>1</truncated>
		<difficult>0</difficult>
		<bndbox>
			<xmin>1</xmin>
			<ymin>655</ymin>
			<xmax>257</xmax>
			<ymax>909</ymax>
		</bndbox>
	</object>
</annotation>
